multiple_annotators_segmentation/__init__.py
multiple_annotators_segmentation/dataloaders/__init__.py
multiple_annotators_segmentation/dataloaders/crowd_seg_dataloader.py
multiple_annotators_segmentation/datasets/__init__.py
multiple_annotators_segmentation/datasets/oxfordIiitpet_msa.py
multiple_annotators_segmentation/losses/__init__.py
multiple_annotators_segmentation/losses/dice_loss.py
multiple_annotators_segmentation/losses/noisy_labels_loss_tf.py
multiple_annotators_segmentation/metrics/__init__.py
multiple_annotators_segmentation/metrics/dice.py
multiple_annotators_segmentation/metrics/jaccard.py
multiple_annotators_segmentation/metrics/sensitivity.py
multiple_annotators_segmentation/metrics/specificity.py
multiple_annotators_segmentation/models/__init__.py
multiple_annotators_segmentation/models/crowd_segmentation_model.py
multiple_annotators_segmentation/trainers/__init__.py
multiple_annotators_segmentation/trainers/crow_seg_training.py
multiple_annotators_segmentation/utils/__init__.py
multiple_annotators_segmentation/utils/performance_measures_crowd_seg_model.py
multiple_annotators_segmentation/utils/random_sample_visualization.py
multiple_annotators_segmentation/utils/sample_performance_visualization.py
multiple_annotators_segmentation-0.1.5.7.dist-info/LICENSE
multiple_annotators_segmentation-0.1.5.7.dist-info/METADATA
multiple_annotators_segmentation-0.1.5.7.dist-info/WHEEL
multiple_annotators_segmentation-0.1.5.7.dist-info/top_level.txt
multiple_annotators_segmentation-0.1.5.7.dist-info/RECORD
