Metadata-Version: 2.1
Name: multiple_annotators_segmentation
Version: 0.1.5.7
Summary: Library for multiple annotators segmentation, using custom Losses and Keras models
Home-page: https://github.com/UN-GCPDS/python-gcpds.multiple_annotators_segmentation.git
Author: Lucas Iturriago
Author-email: liturriago@unal.edu.co
License: LICENSE
License-File: LICENSE
Requires-Dist: tensorflow
Requires-Dist: matplotlib
Requires-Dist: numpy
Requires-Dist: wandb
